[{"id":"1","colorR":0,"colorG":0,"colorB":0,"contenido":"\"\\\"null\\\"\"","fin":{"y":188,"x":883},"inicio":{"y":140,"x":376},"alto":48,"ancho":507},{"id":"2","colorR":0,"colorG":0,"colorB":0,"contenido":"\"\\\"null\\\"\"","fin":{"y":273,"x":871},"inicio":{"y":227,"x":380},"alto":46,"ancho":491},{"id":"3","colorR":0,"colorG":0,"colorB":0,"contenido":"\"\\\"null\\\"\"","fin":{"y":320,"x":911},"inicio":{"y":292,"x":367},"alto":28,"ancho":544},{"id":"213","colorR":0,"colorG":0,"colorB":0,"contenido":"\"null\"","fin":{"y":445,"x":373},"inicio":{"y":401,"x":295},"alto":44,"ancho":78},{"id":"333","colorR":72,"colorG":0,"colorB":0,"contenido":"null","fin":{"y":308,"x":197},"inicio":{"y":232,"x":152},"alto":76,"ancho":45},{"id":"55","colorR":35,"colorG":202,"colorB":155,"contenido":null,"fin":{"y":413,"x":291},"inicio":{"y":342,"x":101},"alto":71,"ancho":190},{"id":"5","colorR":189,"colorG":61,"colorB":78,"contenido":null,"fin":{"y":211,"x":307},"inicio":{"y":132,"x":214},"alto":79,"ancho":93},{"id":"2587","colorR":72,"colorG":24,"colorB":144,"contenido":null,"fin":{"y":122,"x":134},"inicio":{"y":70,"x":70},"alto":52,"ancho":64}]